marlonpy/__init__.py
marlonpy/Conversions/ConvTest.py
marlonpy/Conversions/ConversionBinary.py
marlonpy/Conversions/ConversionIeee.py
marlonpy/Conversions/__init__.py
marlonpy/DifferentialEquations/RungeKutta4th.py
marlonpy/DifferentialEquations/__init__.py
marlonpy/LinearRegression/LinearRegression.py
marlonpy/LinearRegression/__init__.py
marlonpy/NumericalDerivation/__init__.py
marlonpy/NumericalDerivation/derivative.py
marlonpy/NumericalIntegration/GaussLegendre.py
marlonpy/NumericalIntegration/Simpson38.py
marlonpy/NumericalIntegration/TrapezoidalRule.py
marlonpy/NumericalIntegration/__init__.py
marlonpy/Roots/BisectionMethod.py
marlonpy/Roots/FixedPoint.py
marlonpy/Roots/NewtonRaphson.py
marlonpy/Roots/RegulaFalsi.py
marlonpy/Roots/SecantMethod.py
marlonpy/Roots/__init__.py
marlonpy/SystemEquations/Crout.py
marlonpy/SystemEquations/DDM.py
marlonpy/SystemEquations/Doolittle.py
marlonpy/SystemEquations/GaussSeidel.py
marlonpy/SystemEquations/Jacobi.py
marlonpy/SystemEquations/__init__.py
marlonpy/Taylor/TaylorSeries.py
marlonpy/Taylor/__init__.py
marlonpy-1.2.0.dist-info/METADATA
marlonpy-1.2.0.dist-info/WHEEL
marlonpy-1.2.0.dist-info/top_level.txt
marlonpy-1.2.0.dist-info/RECORD
