Metadata-Version: 2.1
Name: marlonpy
Version: 1.2.0
Summary: A package for numerical methods in Python
Home-page: https://github.com/LCCastillo03/NumericalMethods
Author: Gabriela Bula, Lena Castillo, Edgar Garcia
Author-email: 
Classifier: Programming Language :: Python :: 3
Classifier: License :: OSI Approved :: MIT License
Classifier: Operating System :: OS Independent
Requires-Python: >=3.10.12
Requires-Dist: numpy
Requires-Dist: sympy
Requires-Dist: tabulate
